{
  "files": {
    "blocks": {
      "added": [
        "acacia_sign",
        "acacia_wall_sign",
        "andesite_slab",
        "andesite_stairs",
        "andesite_wall",
        "bamboo",
        "bamboo_sapling",
        "barrel",
        "bell",
        "birch_sign",
        "birch_wall_sign",
        "blast_furnace",
        "brick_wall",
        "campfire",
        "cartography_table",
        "composter",
        "cornflower",
        "cut_red_sandstone_slab",
        "cut_sandstone_slab",
        "dark_oak_sign",
        "dark_oak_wall_sign",
        "diorite_slab",
        "diorite_stairs",
        "diorite_wall",
        "end_stone_brick_slab",
        "end_stone_brick_stairs",
        "end_stone_brick_wall",
        "fletching_table",
        "granite_slab",
        "granite_stairs",
        "granite_wall",
        "grindstone",
        "jigsaw",
        "jungle_sign",
        "jungle_wall_sign",
        "lantern",
        "lectern",
        "lily_of_the_valley",
        "loom",
        "mossy_cobblestone_slab",
        "mossy_cobblestone_stairs",
        "mossy_stone_brick_slab",
        "mossy_stone_brick_stairs",
        "mossy_stone_brick_wall",
        "nether_brick_wall",
        "oak_sign",
        "oak_wall_sign",
        "polished_andesite_slab",
        "polished_andesite_stairs",
        "polished_diorite_slab",
        "polished_diorite_stairs",
        "polished_granite_slab",
        "polished_granite_stairs",
        "potted_bamboo",
        "potted_cornflower",
        "potted_lily_of_the_valley",
        "potted_wither_rose",
        "prismarine_wall",
        "red_nether_brick_slab",
        "red_nether_brick_stairs",
        "red_nether_brick_wall",
        "red_sandstone_wall",
        "sandstone_wall",
        "scaffolding",
        "smithing_table",
        "smoker",
        "smooth_quartz_slab",
        "smooth_quartz_stairs",
        "smooth_red_sandstone_slab",
        "smooth_red_sandstone_stairs",
        "smooth_sandstone_slab",
        "smooth_sandstone_stairs",
        "smooth_stone_slab",
        "spruce_sign",
        "spruce_wall_sign",
        "stonecutter",
        "stone_brick_wall",
        "stone_stairs",
        "sweet_berry_bush",
        "wither_rose"
      ],
      "changed": [
        "note_block"
      ],
      "removed": [
        "sign",
        "wall_sign"
      ]
    },
    "commands": {
      "added": [
        "loot",
        "schedule",
        "teammsg",
        "tm"
      ],
      "changed": [
        "data",
        "debug",
        "execute",
        "gamerule",
        "locate"
      ]
    },
    "registries": {
      "added": [
        "activity",
        "biome",
        "biome_source_type",
        "block_entity_type",
        "carver",
        "chunk_generator_type",
        "chunk_status",
        "custom_stat",
        "decorator",
        "dimension_type",
        "enchantment",
        "entity_type",
        "feature",
        "fluid",
        "loot_table",
        "memory_module_type",
        "menu",
        "mob_effect",
        "motive",
        "particle_type",
        "point_of_interest_type",
        "potion",
        "recipe_serializer",
        "recipe_type",
        "rule_test",
        "schedule",
        "sensor_type",
        "sound_event",
        "stat_type",
        "structure_feature",
        "structure_piece",
        "structure_pool_element",
        "structure_processor",
        "surface_builder",
        "villager_profession",
        "villager_type"
      ],
      "changed": [
        "advancement",
        "block",
        "command",
        "item",
        "recipe",
        "tag"
      ]
    }
  }
}